chromastone/__init__.py
chromastone/chromastone.py
chromastone-0.2.6.dist-info/LICENSE
chromastone-0.2.6.dist-info/METADATA
chromastone-0.2.6.dist-info/WHEEL
chromastone-0.2.6.dist-info/top_level.txt
chromastone-0.2.6.dist-info/RECORD
