Metadata-Version: 2.1
Name: chromastone
Version: 0.2.6
Summary: A Python application for powering other python applications to send SMS messages globally with number validation and restrictions by Tarmica Chiwara
Home-page: https://github.com/lordskyzw/chromastone
Author: Tarmica Chiwara
Author-email: lilskyforever@gmail.com
License: UNKNOWN
Platform: UNKNOWN
Classifier: Programming Language :: Python :: 3
Classifier: License :: OSI Approved :: MIT License
Classifier: Operating System :: OS Independent
Requires-Python: >=3.9
License-File: LICENSE
Requires-Dist: requests
Requires-Dist: pydantic
